birdwell/net/__init__.py
birdwell/net/agent.py
birdwell/net/vpn.py
birdwell_net-0.0.2rc17.dev1.dist-info/LICENSE
birdwell_net-0.0.2rc17.dev1.dist-info/METADATA
birdwell_net-0.0.2rc17.dev1.dist-info/WHEEL
birdwell_net-0.0.2rc17.dev1.dist-info/top_level.txt
birdwell_net-0.0.2rc17.dev1.dist-info/RECORD
