Metadata-Version: 2.1
Name: birdwell-net
Version: 0.0.2rc17.dev1
Summary: networking utilities submodule of the birdwell namespace
Author-email: jcbirdwell <jcbirdwell@gmail.com>
License: MIT License
Classifier: Development Status :: 3 - Alpha
Requires-Python: >=3.12
License-File: LICENSE
Requires-Dist: birdwell-utils >=2.0.1rc7.dev1
